zensols/edusenti/__init__.py
zensols/edusenti/app.py
zensols/edusenti/cli.py
zensols/edusenti/domain.py
zensols/edusenti/resources/app.conf
zensols/edusenti/resources/default.conf
zensols/edusenti/resources/obj.yml
zensols.edusenti-0.0.1.dist-info/METADATA
zensols.edusenti-0.0.1.dist-info/WHEEL
zensols.edusenti-0.0.1.dist-info/entry_points.txt
zensols.edusenti-0.0.1.dist-info/top_level.txt
zensols.edusenti-0.0.1.dist-info/RECORD
