Metadata-Version: 2.1
Name: zensols.edusenti
Version: 0.0.1
Summary: Pretraining and sentiment student to instructor review sentiment corpora and analysis.
Home-page: https://github.com/plandes/edusenti
Download-URL: https://github.com/plandes/edusenti/releases/download/v0.0.1/zensols.edusenti-0.0.1-py3-none-any.whl
Author: Paul Landes
Author-email: landes@mailc.net
Keywords: tooling
Requires-Dist: zensols.deepnlp ~=1.13.0
